PyNeel-0.8.21.dist-info/DESCRIPTION.rst
PyNeel-0.8.21.dist-info/METADATA
PyNeel-0.8.21.dist-info/RECORD
PyNeel-0.8.21.dist-info/WHEEL
PyNeel-0.8.21.dist-info/metadata.json
PyNeel-0.8.21.dist-info/top_level.txt
pyneel/__init__.py
pyneel/address.py
pyneel/asset.py
pyneel/crypto.py
pyneel/order.py
